README.md
botsfordiscordapi.py
setup.py
botsfordiscordapi.egg-info/PKG-INFO
botsfordiscordapi.egg-info/SOURCES.txt
botsfordiscordapi.egg-info/dependency_links.txt
botsfordiscordapi.egg-info/not-zip-safe
botsfordiscordapi.egg-info/requires.txt
botsfordiscordapi.egg-info/top_level.txt