Metadata-Version: 1.0
Name: botsfordiscordapi
Version: 0.4
Summary: A bots for discord api handler made by Luke#6723
Home-page: https://gitlab.com/Luke-6723/botsfordiscordapi
Author: UNKNOWN
Author-email: UNKNOWN
License: UNKNOWN
Platform: UNKNOWN
